spams/__init__.py
spams/spams.py
spams/.dylibs/libomp.dylib
test/boat.png
test/test_linalg.py
test/lena.png
test/test_decomp.py
test/test_dictLearn.py
test/test_prox.py
spams_wrap/__init__.py
spams_wrap/spams_wrap.py
spams_wrap/_spams_wrap.cpython-314-darwin.so
spams_bin-2.6.13.dist-info/RECORD
spams_bin-2.6.13.dist-info/WHEEL
spams_bin-2.6.13.dist-info/METADATA
