Metadata-Version: 2.1
Name: spams-bin
Version: 2.6.13
Summary: Python interface for SPAMS - binary wheels with openblas (mac, linux, windows)
License: GPLv2
Requires-Python: >=3.9.0
Requires-Dist: numpy>=1.21.3
Requires-Dist: scipy>=1.5
Provides-Extra: test
Requires-Dist: Pillow>=6.0; extra == "test"
